rightprice/__init__.py
rightprice/__main__.py
rightprice/cli.py
rightprice/error.py
rightprice/house.py
rightprice/sold_prices.py
rightprice-0.2.0.dist-info/METADATA
rightprice-0.2.0.dist-info/WHEEL
rightprice-0.2.0.dist-info/entry_points.txt
rightprice-0.2.0.dist-info/licenses/LICENSE
rightprice-0.2.0.dist-info/RECORD
