Metadata-Version: 2.4
Name: rightprice
Version: 0.2.0
Summary: What is the right price for your property of interest?
Author: David Zhang
License: MIT License
License-File: LICENSE
Requires-Python: >=3.13
Requires-Dist: beautifulsoup4==4.14.3
Requires-Dist: click==8.3.1
Requires-Dist: pandas==2.3.3
Requires-Dist: polars==1.36.1
Requires-Dist: pydantic==2.12.5
Requires-Dist: requests==2.32.5
Provides-Extra: build
Requires-Dist: build==1.3.0; extra == 'build'
Provides-Extra: dev
Requires-Dist: pre-commit==4.3.0; extra == 'dev'
Requires-Dist: pytest-cov==6.0.0; extra == 'dev'
Requires-Dist: pytest==8.4.1; extra == 'dev'
Requires-Dist: responses==0.25.3; extra == 'dev'
